pykcalc/__init__.py
pykcalc-0.1.dist-info/Licence.txt
pykcalc-0.1.dist-info/METADATA
pykcalc-0.1.dist-info/WHEEL
pykcalc-0.1.dist-info/top_level.txt
pykcalc-0.1.dist-info/RECORD
