Metadata-Version: 2.1
Name: pykcalc
Version: 0.1
Summary: This is a calculator package
Home-page: UNKNOWN
Author: krishna jain
Author-email: UNKNOWN
License: UNKNOWN
Platform: UNKNOWN
